opencxr/__init__.py
opencxr/algorithms/__init__.py
opencxr/algorithms/base_algorithm.py
opencxr/algorithms/cxrstandardization/__init__.py
opencxr/algorithms/heartsegmentation/__init__.py
opencxr/algorithms/heartsegmentation/model.py
opencxr/algorithms/imagesorter/__init__.py
opencxr/algorithms/imagesorter/preprocess.py
opencxr/algorithms/lungsegmentation/__init__.py
opencxr/algorithms/lungsegmentation/model.py
opencxr/utils/__init__.py
opencxr/utils/file_io.py
opencxr/utils/mask_crop.py
opencxr/utils/normalization.py
opencxr/utils/resize_rescale.py
opencxr/utils/rotate_flip_invert.py
opencxr-1.3.14.dist-info/LICENSE
opencxr-1.3.14.dist-info/METADATA
opencxr-1.3.14.dist-info/WHEEL
opencxr-1.3.14.dist-info/top_level.txt
opencxr-1.3.14.dist-info/RECORD
