Metadata-Version: 2.1
Name: opencxr
Version: 1.3.14
Summary: a collection of algorithms for processing of chest radiograph (CXR) images
Home-page: https://github.com/DIAGNijmegen/opencxr
Author: Keelin Murphy
Author-email: keelin.murphy@radboudumc.nl
License: Apache 2.0
Keywords: opencxr
License-File: LICENSE
Requires-Dist: wget ==3.2
Requires-Dist: tensorflow ==2.11.0
Requires-Dist: SimpleITK ==2.2.1
Requires-Dist: keras ==2.11.0
Requires-Dist: pydicom ==2.4.3
Requires-Dist: pypng ==0.20220715.0
Requires-Dist: scikit-image ==0.17.2
Requires-Dist: scikit-build ==0.17.6
Requires-Dist: numpy ==1.21.6
